pseutopy/__init__.py
pseutopy/grammar_parser.py
pseutopy/pseutopy.py
pseutopy/builder/__init__.py
pseutopy/builder/ast_parser.py
pseutopy/grammars/cn.lark
pseutopy/grammars/en.lark
pseutopy/grammars/fr.lark
pseutopy/grammars/python.lark
pseutopy-3.0.8.dist-info/LICENSE
pseutopy-3.0.8.dist-info/METADATA
pseutopy-3.0.8.dist-info/WHEEL
pseutopy-3.0.8.dist-info/top_level.txt
pseutopy-3.0.8.dist-info/RECORD
