Metadata-Version: 2.1
Name: pseutopy
Version: 3.0.8
Summary: PseuToPy is a package that transpiles pseudocode into its equivalent Python code
Home-page: https://github.com/PseuToPy/PseuToPy
Author: Patrick Wang
Author-email: patrick.wang@pseutopy.com
License: UNKNOWN
Project-URL: Bug Tracker, https://github.com/PseuToPy/PseuToPy/issues
Platform: UNKNOWN
Classifier: Development Status :: 4 - Beta
Classifier: Intended Audience :: Education
Classifier: Topic :: Education
Classifier: Programming Language :: Python :: 3
Requires-Python: >=3.6
License-File: LICENSE
Requires-Dist: astor (==0.8.0)
Requires-Dist: lark-parser (==0.11.2)
